powerfuldeveloper_base/__init__.py
powerfuldeveloper_base/commands.py
powerfuldeveloper_base-0.0.6.dist-info/LICENSE
powerfuldeveloper_base-0.0.6.dist-info/METADATA
powerfuldeveloper_base-0.0.6.dist-info/WHEEL
powerfuldeveloper_base-0.0.6.dist-info/top_level.txt
powerfuldeveloper_base-0.0.6.dist-info/RECORD
